{
    "time_to_first_node": "0.0s",
    "dual_bound_at_root": 9.0,
    "primal_bound_at_root": 10.0,
    "final_gap": 0.0,
    "primal_bound": 9.0,
    "dual_bound": 9.0,
    "number_of_nodes": 201,
    "instance_name": "t84_pr76",
    "timelimit": 7200,
    "total_time": 422.83,
    "solution": [
        "t_[18, 32, 3, 56, 22, 48, 66, 37, 34, 18]",
        "checking cycle [18, 32, 3, 56, 22, 48, 66, 37, 34, 18]",
        "[18, 32, 3, 56, 22, 48, 66, 37, 34, 18] 15747 15167",
        "t_[24, 14, 61, 72, 52, 58, 35, 46, 20, 2, 31, 24]",
        "checking cycle [24, 14, 61, 72, 52, 58, 35, 46, 20, 2, 31, 24]",
        "[24, 14, 61, 72, 52, 58, 35, 46, 20, 2, 31, 24] 14168 13297",
        "t_[62, 6, 5, 0, 41, 53, 62]",
        "checking cycle [62, 6, 5, 0, 41, 53, 62]",
        "[62, 6, 5, 0, 41, 53, 62] 16240 14802",
        "t_[49, 1, 25, 29, 43, 51, 12, 27, 45, 44, 15, 70, 49]",
        "checking cycle [49, 1, 25, 29, 43, 51, 12, 27, 45, 44, 15, 70, 49]",
        "[49, 1, 25, 29, 43, 51, 12, 27, 45, 44, 15, 70, 49] 14814 13707",
        "[74, 26, 60, 9, 13, 21, 40, 74]",
        "checking cycle [74, 26, 60, 9, 13, 21, 40, 74]",
        "[74, 26, 60, 9, 13, 21, 40, 74] 13914 13853",
        "[71, 47, 57, 53, 19, 63, 39, 69, 11, 71]",
        "checking cycle [71, 47, 57, 53, 19, 63, 39, 69, 11, 71]",
        "[71, 47, 57, 53, 19, 63, 39, 69, 11, 71] 14716 14375",
        "[42, 23, 16, 4, 30, 17, 8, 10, 42]",
        "checking cycle [42, 23, 16, 4, 30, 17, 8, 10, 42]",
        "[42, 23, 16, 4, 30, 17, 8, 10, 42] 20585 20522",
        "[75, 52, 68, 7, 36, 64, 55, 38, 65, 54, 75]",
        "checking cycle [75, 52, 68, 7, 36, 64, 55, 38, 65, 54, 75]",
        "[75, 52, 68, 7, 36, 64, 55, 38, 65, 54, 75] 13754 13686",
        "[75, 50, 59, 51, 67, 33, 35, 73, 28, 75]",
        "checking cycle [75, 50, 59, 51, 67, 33, 35, 73, 28, 75]",
        "[75, 50, 59, 51, 67, 33, 35, 73, 28, 75] 13754 12725"
    ]
}