{
    "time_to_first_node": "0.3s",
    "dual_bound_at_root": 7.0,
    "primal_bound_at_root": 7.0,
    "final_gap": 0.0,
    "primal_bound": 7.0,
    "dual_bound": 7.0,
    "number_of_nodes": 1,
    "instance_name": "at62_ftv33",
    "timelimit": 7200,
    "total_time": 0.35,
    "solution": [
        "[8, 4, 3, 2, 8]",
        "checking cycle [8, 4, 3, 2, 8]",
        "[8, 4, 3, 2, 8] 558 480",
        "[29, 18, 22, 19, 29]",
        "checking cycle [29, 18, 22, 19, 29]",
        "[29, 18, 22, 19, 29] 271 229",
        "[31, 15, 6, 20, 31]",
        "checking cycle [31, 15, 6, 20, 31]",
        "[31, 15, 6, 20, 31] 245 232",
        "[33, 13, 23, 7, 33]",
        "checking cycle [33, 13, 23, 7, 33]",
        "[33, 13, 23, 7, 33] 230 177",
        "[27, 16, 25, 1, 5, 26, 27]",
        "checking cycle [27, 16, 25, 1, 5, 26, 27]",
        "[27, 16, 25, 1, 5, 26, 27] 280 273",
        "[28, 0, 14, 24, 17, 28]",
        "checking cycle [28, 0, 14, 24, 17, 28]",
        "[28, 0, 14, 24, 17, 28] 275 237",
        "[32, 21, 9, 10, 12, 30, 11, 32]",
        "checking cycle [32, 21, 9, 10, 12, 30, 11, 32]",
        "[32, 21, 9, 10, 12, 30, 11, 32] 234 234"
    ]
}